{
  "menu": [
    {
      "name": "Website Checker",
      "file": "website.py"
    },
    {
      "name": "Sms Bomber",
      "file": "sms.py"
    },
    {
      "name": "Sosyal Medya Tarayıcı",
      "file": "username_scanner.py"
    },
    {
      "name": "Müzik indirme",
      "file": "music.py"
    },
    {
      "name": "Güncelleme Kontrol",
      "file": "version.py"
    },
    {
      "name": "Proxy Tarayıcı",
      "file": "proxy.py"
    },
    {
      "name": "Exxen Checker",
      "file": "exxen.py"
    },
    {
      "name": "BluTv Checker",
      "file": "blutv.py"
    }
  ]
}
